xdmf_dolfin_fix/__init__.py
xdmf_dolfin_fix/cli.py
xdmf_dolfin_fix/convert.py
xdmf_dolfin_fix/node_reordering.py
xdmf_dolfin_fix/xdmf_dolfin_fix.py
xdmf_dolfin_fix/xdmf_mesh.py
xdmf_dolfin_fix-0.6.2.dist-info/LICENSE
xdmf_dolfin_fix-0.6.2.dist-info/METADATA
xdmf_dolfin_fix-0.6.2.dist-info/WHEEL
xdmf_dolfin_fix-0.6.2.dist-info/entry_points.txt
xdmf_dolfin_fix-0.6.2.dist-info/top_level.txt
xdmf_dolfin_fix-0.6.2.dist-info/RECORD
