Metadata-Version: 2.1
Name: xdmf-dolfin-fix
Version: 0.6.2
Summary: A tiny package to modify the node order of quadratic triangles and tets in a xdmf-hdf mesh to work with FEniCS/DOLFIN.
Home-page: https://github.com/TTitscher/xdmf_dolfin_fix
Author: Thomas Titscher
Author-email: thomas.titscher@gmail.com
License: UNKNOWN
Platform: UNKNOWN
Classifier: Programming Language :: Python :: 3
Classifier: License :: OSI Approved :: MIT License
Classifier: Operating System :: OS Independent
Requires-Dist: h5py
Requires-Dist: lxml
Requires-Dist: meshio
